bluetti_mqtt/__init__.py
bluetti_mqtt/bus.py
bluetti_mqtt/device_handler.py
bluetti_mqtt/discovery_cli.py
bluetti_mqtt/logger_cli.py
bluetti_mqtt/mqtt_client.py
bluetti_mqtt/server_cli.py
bluetti_mqtt/bluetooth/__init__.py
bluetti_mqtt/bluetooth/client.py
bluetti_mqtt/bluetooth/exc.py
bluetti_mqtt/bluetooth/manager.py
bluetti_mqtt/core/__init__.py
bluetti_mqtt/core/commands.py
bluetti_mqtt/core/utils.py
bluetti_mqtt/core/devices/__init__.py
bluetti_mqtt/core/devices/ac200m.py
bluetti_mqtt/core/devices/ac300.py
bluetti_mqtt/core/devices/ac500.py
bluetti_mqtt/core/devices/ac60.py
bluetti_mqtt/core/devices/bluetti_device.py
bluetti_mqtt/core/devices/eb3a.py
bluetti_mqtt/core/devices/ep500.py
bluetti_mqtt/core/devices/ep500p.py
bluetti_mqtt/core/devices/ep600.py
bluetti_mqtt/core/devices/struct.py
bluetti_mqtt-0.15.0.dist-info/LICENSE
bluetti_mqtt-0.15.0.dist-info/METADATA
bluetti_mqtt-0.15.0.dist-info/WHEEL
bluetti_mqtt-0.15.0.dist-info/entry_points.txt
bluetti_mqtt-0.15.0.dist-info/top_level.txt
bluetti_mqtt-0.15.0.dist-info/RECORD
