Metadata-Version: 2.1
Name: bluetti-mqtt
Version: 0.15.0
Summary: MQTT interface to Bluetti power stations
Home-page: http://github.com/warhammerkid/bluetti_mqtt
Author: Stephen Augenstein
Author-email: perl.programmer@gmail.com
License: MIT
Classifier: Development Status :: 3 - Alpha
Classifier: Programming Language :: Python :: 3
Classifier: License :: OSI Approved :: MIT License
Classifier: Operating System :: OS Independent
Requires-Python: >=3.7
License-File: LICENSE
